{
  "1": {
    "3025|04": [
      "04:32:00",
      "05:32:00",
      "06:02:00",
      "06:32:00",
      "07:02:00",
      "07:32:00",
      "08:02:00",
      "08:32:00",
      "09:02:00",
      "09:37:00",
      "10:17:00",
      "10:57:00",
      "11:37:00",
      "12:17:00",
      "12:57:00",
      "13:37:00",
      "14:17:00",
      "14:52:00",
      "15:22:00",
      "15:52:00",
      "16:22:00",
      "16:52:00",
      "17:22:00",
      "17:52:00",
      "18:22:00",
      "19:02:00",
      "19:47:00",
      "20:27:00",
      "21:07:00",
      "21:47:00",
      "22:27:00",
      "23:35:00"
    ],
    "4181|01": [
      "04:38:00",
      "05:38:00",
      "06:08:00",
      "06:38:00",
      "07:08:00",
      "07:38:00",
      "08:08:00",
      "08:38:00",
      "09:08:00",
      "09:43:00",
      "10:23:00",
      "11:03:00",
      "11:43:00",
      "12:23:00",
      "13:03:00",
      "13:43:00",
      "14:23:00",
      "14:58:00",
      "15:28:00",
      "15:58:00",
      "16:28:00",
      "16:58:00",
      "17:28:00",
      "17:58:00",
      "18:28:00",
      "19:08:00",
      "19:53:00",
      "20:33:00",
      "21:13:00",
      "21:53:00",
      "22:33:00",
      "23:41:00"
    ],
    "4182|02": [
      "04:34:00",
      "05:34:00",
      "06:04:00",
      "06:34:00",
      "07:04:00",
      "07:34:00",
      "08:04:00",
      "08:34:00",
      "09:04:00",
      "09:39:00",
      "10:19:00",
      "10:59:00",
      "11:39:00",
      "12:19:00",
      "12:59:00",
      "13:39:00",
      "14:19:00",
      "14:54:00",
      "15:24:00",
      "15:54:00",
      "16:24:00",
      "16:54:00",
      "17:24:00",
      "17:54:00",
      "18:24:00",
      "19:04:00",
      "19:49:00",
      "20:29:00",
      "21:09:00",
      "21:49:00",
      "22:29:00",
      "23:37:00"
    ],
    "4359|01": [
      "04:42:00",
      "05:42:00",
      "06:12:00",
      "06:42:00",
      "07:12:00",
      "07:42:00",
      "08:12:00",
      "08:42:00",
      "09:12:00",
      "09:47:00",
      "10:27:00",
      "11:07:00",
      "11:47:00",
      "12:27:00",
      "13:07:00",
      "13:47:00",
      "14:27:00",
      "15:02:00",
      "15:32:00",
      "16:02:00",
      "16:32:00",
      "17:02:00",
      "17:32:00",
      "18:02:00",
      "18:32:00",
      "19:12:00",
      "19:57:00",
      "20:37:00",
      "21:17:00",
      "21:57:00",
      "22:37:00",
      "23:45:00"
    ],
    "4358|01": [
      "04:41:00",
      "05:41:00",
      "06:11:00",
      "06:41:00",
      "07:11:00",
      "07:41:00",
      "08:11:00",
      "08:41:00",
      "09:11:00",
      "09:46:00",
      "10:26:00",
      "11:06:00",
      "11:46:00",
      "12:26:00",
      "13:06:00",
      "13:46:00",
      "14:26:00",
      "15:01:00",
      "15:31:00",
      "16:01:00",
      "16:31:00",
      "17:01:00",
      "17:31:00",
      "18:01:00",
      "18:31:00",
      "19:11:00",
      "19:56:00",
      "20:36:00",
      "21:16:00",
      "21:56:00",
      "22:36:00",
      "23:44:00"
    ],
    "4361|01": [
      "04:44:00",
      "05:44:00",
      "06:14:00",
      "06:44:00",
      "07:14:00",
      "07:44:00",
      "08:14:00",
      "08:44:00",
      "09:14:00",
      "09:49:00",
      "10:29:00",
      "11:09:00",
      "11:49:00",
      "12:29:00",
      "13:09:00",
      "13:49:00",
      "14:29:00",
      "15:04:00",
      "15:34:00",
      "16:04:00",
      "16:34:00",
      "17:04:00",
      "17:34:00",
      "18:04:00",
      "18:34:00",
      "19:14:00",
      "19:59:00",
      "20:39:00",
      "21:19:00",
      "21:59:00",
      "22:39:00",
      "23:47:00"
    ],
    "4360|01": [
      "04:43:00",
      "05:43:00",
      "06:13:00",
      "06:43:00",
      "07:13:00",
      "07:43:00",
      "08:13:00",
      "08:43:00",
      "09:13:00",
      "09:48:00",
      "10:28:00",
      "11:08:00",
      "11:48:00",
      "12:28:00",
      "13:08:00",
      "13:48:00",
      "14:28:00",
      "15:03:00",
      "15:33:00",
      "16:03:00",
      "16:33:00",
      "17:03:00",
      "17:33:00",
      "18:03:00",
      "18:33:00",
      "19:13:00",
      "19:58:00",
      "20:38:00",
      "21:18:00",
      "21:58:00",
      "22:38:00",
      "23:46:00"
    ],
    "4182|01": [
      "04:47:00",
      "05:47:00",
      "06:17:00",
      "06:47:00",
      "07:17:00",
      "07:47:00",
      "08:17:00",
      "08:47:00",
      "09:17:00",
      "09:52:00",
      "10:32:00",
      "11:12:00",
      "11:52:00",
      "12:32:00",
      "13:12:00",
      "13:52:00",
      "14:32:00",
      "15:07:00",
      "15:37:00",
      "16:07:00",
      "16:37:00",
      "17:07:00",
      "17:37:00",
      "18:07:00",
      "18:37:00",
      "19:17:00",
      "20:02:00",
      "20:42:00",
      "21:22:00",
      "22:02:00",
      "22:42:00",
      "23:50:00"
    ]
  }
}